virtool/__init__.py
virtool/account/__init__.py
virtool/account/api.py
virtool/account/data.py
virtool/account/models.py
virtool/account/mongo.py
virtool/account/oas.py
virtool/administrators/__init__.py
virtool/administrators/actions.py
virtool/administrators/api.py
virtool/administrators/data.py
virtool/administrators/models.py
virtool/administrators/oas.py
virtool/analyses/__init__.py
virtool/analyses/api.py
virtool/analyses/checks.py
virtool/analyses/data.py
virtool/analyses/db.py
virtool/analyses/files.py
virtool/analyses/format.py
virtool/analyses/models.py
virtool/analyses/oas.py
virtool/analyses/sql.py
virtool/analyses/utils.py
virtool/api/__init__.py
virtool/api/accept.py
virtool/api/authentication.py
virtool/api/client.py
virtool/api/custom_json.py
virtool/api/errors.py
virtool/api/headers.py
virtool/api/logging.py
virtool/api/policy.py
virtool/api/redirects.py
virtool/api/root.py
virtool/api/routes.py
virtool/api/schema.py
virtool/api/sessions.py
virtool/api/utils.py
virtool/app.py
virtool/authorization/__init__.py
virtool/authorization/client.py
virtool/authorization/connect.py
virtool/authorization/openfga.py
virtool/authorization/permissions.py
virtool/authorization/relationships.py
virtool/authorization/results.py
virtool/bio.py
virtool/blast/__init__.py
virtool/blast/data.py
virtool/blast/db.py
virtool/blast/models.py
virtool/blast/sql.py
virtool/blast/task.py
virtool/blast/transform.py
virtool/blast/utils.py
virtool/cli.py
virtool/config/__init__.py
virtool/config/cls.py
virtool/config/options.py
virtool/data/__init__.py
virtool/data/domain.py
virtool/data/errors.py
virtool/data/events.py
virtool/data/file.py
virtool/data/http.py
virtool/data/layer.py
virtool/data/topg.py
virtool/data/transforms.py
virtool/data/utils.py
virtool/dev/__init__.py
virtool/dev/api.py
virtool/doc.py
virtool/errors.py
virtool/example.py
virtool/fake/__init__.py
virtool/fake/next.py
virtool/fake/providers.py
virtool/fake/values.py
virtool/fake/wrapper.py
virtool/flags.py
virtool-31.11.1.dist-info/WHEEL
virtool-31.11.1.dist-info/entry_points.txt
virtool-31.11.1.dist-info/METADATA
virtool-31.11.1.dist-info/RECORD
