Metadata-Version: 2.4
Name: virtool
Version: 31.11.1
Summary: Viral infection diagnostics using next-generation sequencing
Author: Ian Boyes, Reece Hoffmann, Aman Monga, Blake Smith, Jake Alexander, Josh Moreira, Lilly Roberts, Matthew Curtis, Naomi Schaufele, Ryan Fang, Sebastian Chen, Tiansheng Sui, Bryce Davidson, Christine Wong Chong, Markus Swoveland
License-Expression: MIT
Requires-Dist: aiohttp[speedups]>=3.12,<4.0
Requires-Dist: aiohttp-pydantic>=1.12.1,<2.0.0
Requires-Dist: alembic[tz]>=1.16.2,<2.0.0
Requires-Dist: arrow>=1.3.0,<2.0.0
Requires-Dist: asyncpg>=0.30.0,<1.0.0
Requires-Dist: bcrypt>=4.0.0,<5.0.0
Requires-Dist: biopython>=1.84,<2.0
Requires-Dist: cerberus>=1.3.4,<2.0.0
Requires-Dist: certifi>=2025.6.15,<2026.0.0
Requires-Dist: click>=8.2.1,<9.0.0
Requires-Dist: dictdiffer>=0.9.0,<1.0.0
Requires-Dist: email-validator>=2.0.0,<3.0.0
Requires-Dist: faker>=12.3.3,<38.0.0
Requires-Dist: motor>=3.7.1,<4.0.0
Requires-Dist: openfga-sdk==0.1.1
Requires-Dist: openpyxl>=3.1.5,<4.0.0
Requires-Dist: orjson>=3.10.18,<4.0.0
Requires-Dist: pydantic==1.10.16
Requires-Dist: pyyaml>=6.0.0,<7.0.0
Requires-Dist: semver>=2.13.0,<4.0.0
Requires-Dist: sentry-sdk>=2.30.0,<3.0.0
Requires-Dist: sqlalchemy>=2.0.42
Requires-Dist: structlog-sentry>=2.1.0,<3.0.0
Requires-Dist: visvalingamwyatt>=0.1.4,<1.0.0
Requires-Dist: redis>=6.2.0,<7.0.0
Requires-Dist: enum-tools>=0.13.0,<1.0.0
Requires-Dist: aiofiles>=24.1.0
Requires-Dist: pydantic-factories>=1.17.3
Requires-Dist: pyfixtures>=1.1.0
Maintainer: Ian Boyes, Reece Hoffmann
Requires-Python: >=3.13.7, <3.14
